{
  "id": "tradition-历史唯物主义",
  "slug": "历史唯物主义",
  "entityType": "tradition",
  "name": "历史唯物主义",
  "originalNames": [],
  "summary": "历史唯物主义是本知识库用于组织人物、文本与概念的一项思想传统索引。它不把传统理解为封闭或同质的体系，而用于呈现内部差异、历史传播与跨传统接触。",
  "periodLabel": "跨历史时期",
  "regionLabels": [
    "欧洲"
  ],
  "parentIds": [],
  "relatedTraditionIds": [],
  "personIds": [
    "marx"
  ],
  "conceptIds": [
    "concept-资本",
    "concept-异化",
    "concept-阶级"
  ],
  "sourceIds": [
    "src-marx"
  ],
  "citations": [
    {
      "sourceId": "src-marx",
      "locator": "Sections on alienation, history, capital and emancipation",
      "claim": "支持历史唯物主义的摘要主张：历史唯物主义是本知识库用于组织人物、文本与概念的一项思想传统索引。它不把传统理解为封闭或同质的体系，而用于呈现内部差异、历史传播与跨传统接触。"
    }
  ],
  "contentTier": "index",
  "editorialStatus": "published",
  "version": 1,
  "editedBy": "思想星图编辑组",
  "reviewedBy": "automated-migration-review/v1",
  "lastReviewedAt": "2026-07-18",
  "notes": "由公开演示版数据迁移；后续仍需逐条扩写与学术复核。"
}
